odoo9_addon_l10n_nl_intrastat-9.0.2.0.0-py3.8-nspkg.pth
odoo_addons/l10n_nl_intrastat/README.rst
odoo_addons/l10n_nl_intrastat/__init__.py
odoo_addons/l10n_nl_intrastat/__openerp__.py
odoo_addons/l10n_nl_intrastat/data/report_layouts.xml
odoo_addons/l10n_nl_intrastat/i18n/l10n_nl_intrastat.pot
odoo_addons/l10n_nl_intrastat/i18n/nl.po
odoo_addons/l10n_nl_intrastat/models/__init__.py
odoo_addons/l10n_nl_intrastat/models/l10n_nl_intrastat.py
odoo_addons/l10n_nl_intrastat/report/l10n_nl_intrastat.xml
odoo_addons/l10n_nl_intrastat/report/reports.xml
odoo_addons/l10n_nl_intrastat/security/ir.model.access.csv
odoo_addons/l10n_nl_intrastat/static/description/icon.png
odoo_addons/l10n_nl_intrastat/static/src/css/report.css
odoo_addons/l10n_nl_intrastat/tests/__init__.py
odoo_addons/l10n_nl_intrastat/tests/test_all.py
odoo_addons/l10n_nl_intrastat/views/l10n_nl_intrastat.xml
odoo9_addon_l10n_nl_intrastat-9.0.2.0.0.dist-info/METADATA
odoo9_addon_l10n_nl_intrastat-9.0.2.0.0.dist-info/WHEEL
odoo9_addon_l10n_nl_intrastat-9.0.2.0.0.dist-info/namespace_packages.txt
odoo9_addon_l10n_nl_intrastat-9.0.2.0.0.dist-info/top_level.txt
odoo9_addon_l10n_nl_intrastat-9.0.2.0.0.dist-info/RECORD
